sygna_bridge_util/__init__.py
sygna_bridge_util/api/__init__.py
sygna_bridge_util/api/main.py
sygna_bridge_util/config/__init__.py
sygna_bridge_util/config/main.py
sygna_bridge_util/config/permissionstatus.py
sygna_bridge_util/config/rejectcode.py
sygna_bridge_util/crypto/__init__.py
sygna_bridge_util/crypto/ecies.py
sygna_bridge_util/crypto/main.py
sygna_bridge_util/crypto/sign.py
sygna_bridge_util/crypto/utils.py
sygna_bridge_util/crypto/verify.py
sygna_bridge_util/validator/__init__.py
sygna_bridge_util/validator/validatedata.py
sygna_bridge_util-2.0.3.dist-info/METADATA
sygna_bridge_util-2.0.3.dist-info/WHEEL
sygna_bridge_util-2.0.3.dist-info/top_level.txt
sygna_bridge_util-2.0.3.dist-info/RECORD
