Metadata-Version: 2.1
Name: sygna-bridge-util
Version: 2.0.3
Summary: This is a Python library to help you build servers/services within Sygna Bridge Ecosystem.
Home-page: https://github.com/CoolBitX-Technology/sygna-bridge-util-py
Author: kunming.liu
Author-email: kunming@coolbitx.com
License: MIT
Keywords: sygna-bridge-util sygna bridge sygna-bridge ecosystem
Requires-Python: >=3.11
Requires-Dist: asn1crypto ==1.3.0
Requires-Dist: certifi ==2021.10.8
Requires-Dist: cffi ==1.16.0
Requires-Dist: chardet ==3.0.4
Requires-Dist: coincurve ==13.0.0
Requires-Dist: ecdsa ==0.15
Requires-Dist: eciespy ==0.3.6
Requires-Dist: eth-hash ==0.2.0
Requires-Dist: eth-keys ==0.3.3
Requires-Dist: eth-typing ==2.2.1
Requires-Dist: eth-utils ==1.9.0
Requires-Dist: idna ==2.10
Requires-Dist: pycparser ==2.20
Requires-Dist: pycryptodome ==3.9.8
Requires-Dist: requests ==2.31.0
Requires-Dist: six ==1.15.0
Requires-Dist: toolz ==0.10.0
Requires-Dist: urllib3 ==1.26
Requires-Dist: cytoolz ==0.12.2 ; implementation_name == "cpython"
